layrz_forms/__init__.py
layrz_forms/form.py
layrz_forms/py.typed
layrz_forms/types.py
layrz_forms/fields/__init__.py
layrz_forms/fields/base.py
layrz_forms/fields/boolean.py
layrz_forms/fields/char.py
layrz_forms/fields/email.py
layrz_forms/fields/id.py
layrz_forms/fields/json.py
layrz_forms/fields/number.py
layrz_forms/fields/uuid.py
layrz_forms-2.1.5.dist-info/licenses/LICENSE
layrz_forms-2.1.5.dist-info/METADATA
layrz_forms-2.1.5.dist-info/WHEEL
layrz_forms-2.1.5.dist-info/top_level.txt
layrz_forms-2.1.5.dist-info/RECORD
