Metadata-Version: 2.4
Name: layrz-forms
Version: 2.1.5
Summary: Layrz forms and tools for Python
Author-email: "Golden M, Inc." <software@goldenm.com>
Maintainer-email: Kenny Mochizuki <kenny@goldenm.com>, Miguel Zauzich <miguel@goldenm.com>
License: MIT License
Project-URL: Repository, https://github.com/goldenm-software/layrz-forms
Project-URL: Changelog, https://github.com/goldenm-software/layrz-forms/blob/main/CHANGELOG.md
Keywords: sdk,goldenm,layrz,django forms,django,forms
Classifier: Programming Language :: Python :: 3
Classifier: Programming Language :: Python :: 3.11
Classifier: Programming Language :: Python :: 3.12
Classifier: Programming Language :: Python :: 3.13
Requires-Python: >=3.11
License-File: LICENSE
Dynamic: license-file
